tzx_py_tools/__init__.py
tzx_py_tools/base/__init__.py
tzx_py_tools/base/clock_tool.py
tzx_py_tools/base/database_tool.py
tzx_py_tools/base/easy_type.py
tzx_py_tools/base/file_tool.py
tzx_py_tools/base/fore_rain_data_convert.py
tzx_py_tools/base/image_tool.py
tzx_py_tools/base/rain_convert.py
tzx_py_tools/base/soil_water_tools.py
tzx_py_tools/base/system_tool.py
tzx_py_tools/base/update.py
tzx_py_tools/base/web_tool.py
tzx_py_tools/server/__init__.py
tzx_py_tools/server/clock_server.py
tzx_py_tools-0.0.5.dist-info/LICENSE
tzx_py_tools-0.0.5.dist-info/METADATA
tzx_py_tools-0.0.5.dist-info/WHEEL
tzx_py_tools-0.0.5.dist-info/top_level.txt
tzx_py_tools-0.0.5.dist-info/RECORD
